sqlalchemy_triopg-1.0.1.dist-info/METADATA
sqlalchemy_triopg-1.0.1.dist-info/WHEEL
sqlalchemy_triopg-1.0.1.dist-info/entry_points.txt
sqlalchemy_triopg-1.0.1.dist-info/licenses/LICENSE
sqlalchemy_triopg/__init__.py
sqlalchemy_triopg/py.typed
sqlalchemy_triopg/triopg.py
sqlalchemy_triopg-1.0.1.dist-info/RECORD
