Metadata-Version: 2.1
Name: sqlalchemy-triopg
Version: 1.0.1
Summary: A thin Trio-backed wrapper for SQLAlchemy's asyncpg PostgreSQL driver
Author-Email: Elias Gabriel <me@eliasfgabriel.com>
License: BSD-3-Clause-Clear
Project-URL: Documentation, https://github.com/thearchitector/sqlalchemy-triopg
Project-URL: Changelog, https://github.com/thearchitector/sqlalchemy-triopg/blob/main/CHANGELOG.md
Project-URL: Repository, https://github.com/thearchitector/sqlalchemy-triopg
Requires-Python: >=3.8
Requires-Dist: trio-asyncio>=0.12.0
Requires-Dist: sqlalchemy<2.1,>=1.4.0
Requires-Dist: asyncpg
